{
  "cases": [
    {
      "id": "new_hire",
      "name": "New Hire🎖️",
      "price": 2.49,
      "image": "images/cases/newhires.png",
      "items": [
        { "name": "Syringe Gun", "rarity": "legendary", "price": 0.07, "weight": 900, "image": "images/items/syringe_gun.png" },
        { "name": "Stock Shotgun", "rarity": "legendary", "price": 0.10, "weight": 800, "image": "images/items/shotgun.png" },
        { "name": "Stock Scattergun", "rarity": "legendary", "price": 0.06, "weight": 700, "image": "images/items/stockscatt.png" },
        { "name": "Diamondback", "rarity": "legendary", "price": 0.01, "weight": 700, "image": "images/items/diaback.png" },
        { "name": "Strange Eyelander", "rarity": "strange", "price": 2.15, "weight": 300, "image": "images/items/eyelander.png" },
        { "name": "Strange Force-A-Nature", "rarity": "strange", "price": 1.95, "weight": 300, "image": "images/items/fan.png" },
        { "name": "Stock Minigun", "rarity": "legendary", "price": 0.02, "weight": 600, "image": "images/items/minig.png" },
        { "name": "Stock Flamethrower", "rarity": "legendary", "price": 0.02, "weight": 700, "image": "images/items/flamet.png" },
        { "name": "Stock Rocket Launcher", "rarity": "legendary", "price": 0.01, "weight": 900, "image": "images/items/rr.png" },
        { "name": "Strange Frontier Justice", "rarity": "strange", "price": 3.27, "weight": 450, "image": "images/items/frontjust.png" },
        { "name": "Übersaw", "rarity": "legendary", "price": 0.01, "weight": 700, "image": "images/items/ubersaw.png" },
        { "name": "Bill's Hat", "rarity": "legendary", "price": 8.99, "weight": 300, "image": "images/items/billhat.png" },
        { "name": "Ghost Town Claidheamh Mor", "rarity": "rare", "price": 5.75, "weight": 320, "image": "images/items/spooky.png" },
        { "name": "Helldiver Black Box", "rarity": "rare", "price": 20.19, "weight": 190, "image": "images/items/hellblackbox.png" },
        { "name": "Unusual Terror-Watt Capo's Capper", "rarity": "mythical", "price": 60.99, "weight": 30, "image": "images/items/regrets.png" },
        { "name": "Strange Pistol", "rarity": "strange", "price": 0.89, "weight": 450, "image": "images/items/pistol.png" },
        { "name": "Unusual Miami Nights B-ANKH!", "rarity": "mythical", "price": 111.99, "weight": 15, "image": "images/items/miab.png" },
        { "name": "Unusual Hellfire Well-Rounded Rifleman", "rarity": "collector", "price": 2700.99, "weight": 1, "image": "images/items/unusual1.png" },
        { "name": "Unusual The Dark Doorway Heavy Artillery Officer's Cap", "rarity": "mythical", "price": 130.00, "weight": 10, "image": "images/items/tddh.png" }
      ]
    },
    {
      "id": "sanctuary",
      "name": "Silent Sanctuary⛪",
      "price": 15.00,
      "image": "images/cases/sanctuary.png",
      "items": [
        { "name": "Unusual Magenta Monstrum Vaudville Visor", "rarity": "mythical", "price": 43.30, "weight": 220, "image": "images/items/magmonstrum.png" },
        { "name": "Unusual Flavorsome Sunset Reel Fly Hat", "rarity": "mythical", "price": 54.25, "weight": 230, "image": "images/items/sunreel.png" },
        { "name": "Unusual Smoking Spliting Headache", "rarity": "mythical", "price": 14.99, "weight": 400, "image": "images/items/shs.png" },
        { "name": "Strange Killstreak Big Earner", "rarity": "strange", "price": 4.01, "weight": 1400, "image": "images/items/stbigks.png" },
        { "name": "Smoking Jacket", "rarity": "legendary", "price": 3.61, "weight": 450, "image": "images/items/smokingjacket.png" },
        { "name": "Unusual Sunbeams Killer Exclusive", "rarity": "mythical", "price": 98.61, "weight": 140, "image": "images/items/sunkiller.png" },
        { "name": "Haunted Holy Hunter", "rarity": "haunted", "price": 4.16, "weight": 1900, "image": "images/items/holyhunter.png" },
        { "name": "Strange Dapper Dickens", "rarity": "strange", "price": 8.99, "weight": 1400, "image": "images/items/dapdickens.png" },
        { "name": "Strange L'Etranger", "rarity": "strange", "price": 3.40, "weight": 1200, "image": "images/items/letranger.png" },
        { "name": "Unusual Cosmic Constellations Bruisers Bandanna", "rarity": "mythical", "price": 239.00, "weight": 100, "image": "images/items/cosbruis.png" },
        { "name": "Vintage Vintage Merryweather", "rarity": "vintage", "price": 3.00, "weight": 1600, "image": "images/items/merryweather.png" },
        { "name": "Unusual Baron's Cherished Chaplet Templar's Spirit", "rarity": "mythical", "price": 64.38, "weight": 750, "image": "images/items/tempspirit.png" },
        { "name": "Haunted Fallen Angel", "rarity": "haunted", "price": 1.89, "weight": 1500, "image": "images/items/fallenangel.png" },
        { "name": "Genuine Tomb Readers", "rarity": "genuine", "price": 6.97, "weight": 1400, "image": "images/items/tombread.png" },
        { "name": "Genuine Professional Killstreak Sharp Dresser", "rarity": "genuine", "price": 23.42, "weight": 1300, "image": "images/items/sharpdress.png" },
        { "name": "Unusual Stellar Ascent Ludicrously Lunatic Lunon Fedora", "rarity": "mythical", "price": 62.00, "weight": 170, "image": "images/items/stelfed.png" },
        { "name": "Unusual Green Energy Professional's Panama", "rarity": "mythical", "price": 91.45, "weight": 190, "image": "images/items/greenpanama.png" },
        { "name": "Unusual Searing Plasma Nunhood", "rarity": "mythical", "price": 28.00, "weight": 400, "image": "images/items/spn.png" },
        { "name": "Unusual Atomic Mighty Mitre", "rarity": "mythical", "price": 45.00, "weight": 300, "image": "images/items/amm.png" },
        { "name": "Unusual Ocean Swirl Angel Of Death", "rarity": "mythical", "price": 62.99, "weight": 290, "image": "images/items/oaod.png" },
        { "name": "Unusual Rainbow Reverie Burly Beast", "rarity": "collector", "price": 423.73, "weight": 25, "image": "images/items/sbb1.png" },
        { "name": "The Exorcizor", "rarity": "legendary", "price": 0.03, "weight": 2000, "image": "images/items/exoc.png" },
        { "name": "The Ghastlierest Gibus", "rarity": "legendary", "price": 1.88, "weight": 1000, "image": "images/items/ggibus.png" },
        { "name": "Strange Professional Killstreak Solemn Vow", "rarity": "strange", "price": 5.99, "weight": 1300, "image": "images/items/solemn.png" },
        { "name": "Professional Killstreak Black Rose", "rarity": "collector", "price": 999.99, "weight": 3, "image": "images/items/blackrose.png" },
        { "name": "The Plutonidome", "rarity": "legendary", "price": 0.71, "weight": 350, "image": "images/items/pluto.png" },
        { "name": "Unusual Starstorm Slumber Cranial Carcharodon", "rarity": "mythical", "price": 90.00, "weight": 270, "image": "images/items/starcran.png" },
        { "name": "Genuine Doublecross-Comm", "rarity": "genuine", "price": 5.99, "weight": 500, "image": "images/items/doublecomm.png" },
        { "name": "Unusual Dead Presidents Tundra Top", "rarity": "mythical", "price": 60.00, "weight": 260, "image": "images/items/deadtundra.png" }
      ]
    },
    {
      "id": "robots",
      "name": "🆁🅾🅱🅾🆃🅸🅲🤖",
      "price": 75,
      "image": "images/cases/robots.png",
      "items": [
        { "name": "Collectors Gunslinger", "rarity": "collector", "price": 700.00, "weight": 400, "image": "images/items/gunslinger.png" },
        { "name": "Strange Collectors Manmelter", "rarity": "collector", "price": 350.00, "weight": 550, "image": "images/items/manmelter.png" },
        { "name": "Unusual Nuts n' Bolts Full Metal Drill Hat", "rarity": "mythical", "price": 8.65, "weight": 6000, "image": "images/items/nutdrill.png" },
        { "name": "Unusual Spellbound Bonk Leadwear", "rarity": "mythical", "price": 1750.00, "weight": 170, "image": "images/items/spellbolt.png" },
        { "name": "Unusual Time Warp Metal Slug", "rarity": "mythical", "price": 292.00, "weight": 500, "image": "images/items/warpslug.png" },
        { "name": "Strange Unusual Tesla Coil Modest Metal Pile of Scrap", "rarity": "mythical", "price": 200.00, "weight": 750, "image": "images/items/teslahat.png" },
        { "name": "Unusual Scorching Flames Firewall Helmet", "rarity": "mythical", "price": 152.19, "weight": 1000, "image": "images/items/scorchingfirewall.png" },
        { "name": "Unusual Nuts n' Bolts Stronium Stove Pipe", "rarity": "mythical", "price": 11.76, "weight": 6000, "image": "images/items/nutstove.png" },
        { "name": "Strange Mecha-Medes", "rarity": "strange", "price": 8.91, "weight": 5000, "image": "images/items/mechamedes.png" },
        { "name": "Strange Battery Canteens", "rarity": "strange", "price": 39.99, "weight": 7500, "image": "images/items/batterycanteen.png" },
        { "name": "The Battery Bandolier", "rarity": "legendary", "price": 0.06, "weight": 33000, "image": "images/items/battery.png" },
        { "name": "Unusual Nebula Rusty Reaper", "rarity": "mythical", "price": 635.35, "weight": 400, "image": "images/items/rustynebula.png" },
        { "name": "Unusual Atomic Bolted Bicorn", "rarity": "mythical", "price": 190.00, "weight": 600, "image": "images/items/atomicbicorn.png" },
        { "name": "Unusual Tesla Coil Bananades", "rarity": "mythical", "price": 110.76, "weight": 999, "image": "images/items/teslabananades.png" },
        { "name": "Unusual Cold Cosmos Idiot Box", "rarity": "mythical", "price": 362.84, "weight": 400, "image": "images/items/coldidiot.png" },
        { "name": "Unusual Fragmented Photons Running Man", "rarity": "mythical", "price": 49.99, "weight": 6000, "image": "images/items/runningfrags.png" },
        { "name": "Unusual Halcyon Halo Robotler 2000", "rarity": "collector", "price": 34000.00, "weight": 22, "image": "images/items/halobotler.png" },
        { "name": "Unusual Sapped Glitched Circuit Board", "rarity": "mythical", "price": 173.19, "weight": 800, "image": "images/items/circuitsap.png" },
        { "name": "Unusual Resonation Robro 3000", "rarity": "mythical", "price": 76.00, "weight": 5400, "image": "images/items/robrou.png" },
        { "name": "Haunted Unusual Voltaic Hat Protector Teufort Kight", "rarity": "haunted", "price": 90.00, "weight": 5400, "image": "images/items/tkv.png" },
        { "name": "Unusual Abyssal Aura Scrap Pack", "rarity": "mythical", "price": 29.99, "weight": 8000, "image": "images/items/aurascrap.png" },
        { "name": "Unusual Warp Drive Rogues Rabbit ", "rarity": "mythical", "price": 270.00, "weight": 1300, "image": "images/items/warprabbit.png" }
      ]
     },
    {
      "id": "heavy",
      "name": "Heavy Weapons",
      "price": 10.00,
      "image": "images/cases/theheavy1.png",
      "items": [
        { "name": "Strange Sandvich", "rarity": "strange", "price": 21.93, "weight": 1000, "image": "images/items/sandvich.png" },
        { "name": "Chicken Kiev", "rarity": "legendary", "price": 63.72, "weight": 400, "image": "images/items/kiev.png" },
        { "name": "Sophisticated Smoker ", "rarity": "legendary", "price": 0.65, "weight": 3000, "image": "images/items/sophs.png" },
        { "name": "Brute's Braces", "rarity": "legendary", "price": 0.27, "weight": 4000, "image": "images/items/bb3.png" },
        { "name": "Full Metal Helmet", "rarity": "legendary", "price": 12.40, "weight": 1500, "image": "images/items/fmh.png" },
        { "name": "Red Army Robin", "rarity": "legendary", "price": 0.05, "weight": 2750, "image": "images/items/rar3.png" },
        { "name": "Carl", "rarity": "legendary", "price": 0.19, "weight": 1000, "image": "images/items/carl.png" },
        { "name": "Evil Carl", "rarity": "mythical", "price": 111.76, "weight": 50, "image": "images/items/ecarl.png" },
        { "name": "Unusual Sulphurous Heavy Lifter", "rarity": "mythical", "price": 89.91, "weight": 50, "image": "images/items/ushl.png" },
        { "name": "Strange Battle Baclava", "rarity": "strange", "price": 69.99, "weight": 75, "image": "images/items/sbb0.png" },
        { "name": "Unusual Amaranthine Road Rage", "rarity": "mythical", "price": 30.00, "weight": 530, "image": "images/items/arru.png" },
        { "name": "Heavy's Unusual Eyes of Molten Mannvich", "rarity": "collector", "price": 635.35, "weight": 3, "image": "images/items/eomm.png" },
        { "name": "Officer's Ushanka", "rarity": "legendary", "price":0.08, "weight": 4000, "image": "images/items/ou.png" },
        { "name": "Unusual Malevolent Monoculi Team Captian", "rarity": "mythical", "price": 210.76, "weight": 30, "image": "images/items/mmtc.png" },
        { "name": "Strange Family Business", "rarity": "strange", "price": 2.84, "weight": 3000, "image": "images/items/familyb.png" },
        { "name": "Australium Minigun", "rarity": "legendary", "price": 39.99, "weight": 200, "image": "images/items/aussiemini.png" },
        { "name": "Australium Tomislav", "rarity": "legendary", "price": 39.00, "weight": 200, "image": "images/items/aussietomy.png" },
        { "name": "Heavy's Professional Killstreak Fists", "rarity": "strange", "price": 3.19, "weight": 5000, "image": "images/items/fists.png" },
        { "name": "Strange Holiday Punch", "rarity": "strange", "price": 29.00, "weight": 540, "image": "images/items/holidayp.png" },
        { "name": "Genuine Robo-Sandvich", "rarity": "genuine", "price": 550.00, "weight": 5, "image": "images/items/robos.png" },
        { "name": "Bread Bite", "rarity": "legendary", "price": 12.99, "weight": 3000, "image": "images/items/breadb.png" },
        { "name": "Professional Killstreak Iron Curtain", "rarity": "legendary", "price": 72.00, "weight": 230, "image": "images/items/icurtain.png" },
        { "name": "Unusual Burning Flames Large Luchador", "rarity": "mythical", "price": 190.00, "weight": 45, "image": "images/items/ubfll.png" },
        { "name": "Unusual Demonflame One-Man Army", "rarity": "mythical", "price": 125.00, "weight": 60, "image": "images/items/udoma.png" },
        { "name": "Unusual Ventum Maris Brass Beast", "rarity": "mythical", "price": 73.00, "weight": 90, "image": "images/items/ubrass.png" }
      ]
     },
     {
      "id": "peak",
      "name": "The Peak⛰️",
      "price": 120,
      "image": "images/cases/peak.png",
      "items": [
        { "name": "Collectors Flapjack", "rarity": "collector", "price": 9642.00, "weight": 10, "image": "images/items/flapjack.png" },
        { "name": "Unusual Crystal Crown Breach and Bomb", "rarity": "mythical", "price": 630.00, "weight": 200, "image": "images/items/crybomb.png" },
        { "name": "Unusual Playful Aurora Fuel Injector", "rarity": "mythical", "price": 744.99, "weight": 200, "image": "images/items/pafi.png" },
        { "name": "Unusual Ghosts of Smissmas Time Alcoholic Automoton", "rarity": "mythical", "price": 666.00, "weight": 200, "image": "images/items/gostaa.png" },
        { "name": "Unusual Golstruck Anger", "rarity": "mythical", "price": 505.00, "weight": 200, "image": "images/items/gsa.png" },
        { "name": "Unusual Cosmic Constellations Blizzard Britches", "rarity": "collector", "price": 963.00, "weight": 120, "image": "images/items/ccbb.png" },
        { "name": "Unusual Polar Forecast Doublecross-Comm", "rarity": "mythical", "price": 280.00, "weight": 3500, "image": "images/items/dccp.png" },
        { "name": "Strange Bushi-Dou", "rarity": "strange", "price": 25.76, "weight": 6000, "image": "images/items/bd2.png" },
        { "name": "Unusual Burning Flames Mad Mask", "rarity": "mythical", "price": 2000.00, "weight": 80, "image": "images/items/bfmm.png" },
        { "name": "Unusual Dazzling Constellations Bruiser's Bandanna", "rarity": "mythical", "price": 3075.00, "weight": 75, "image": "images/items/dcbb.png" },
        { "name": "Strange Triggermans Tacticals", "rarity": "strange", "price": 37.56, "weight": 4000, "image": "images/items/trigtact.png" },
        { "name": "Unusual Cold Cosmos Patriot Peak", "rarity": "collector", "price": 8232.00, "weight": 16, "image": "images/items/ppcc.png" },
        { "name": "Unusual Refracting Fractals Field Fatigues", "rarity": "mythical", "price": 94.00, "weight": 3000, "image": "images/items/ffrf.png" },
        { "name": "Unusual Searing Stove Masked Loyalty", "rarity": "mythical", "price": 110.76, "weight": 2000, "image": "images/items/ssml.png" },
        { "name": "Unusual Ring of Fire Lunatics Leathers", "rarity": "mythical", "price": 28.84, "weight": 5000, "image": "images/items/rofll.png" },
        { "name": "Unusual Reverium Irregularis Dead of Night", "rarity": "mythical", "price": 4900.00, "weight": 20, "image": "images/items/udn.png" },
        { "name": "Unusual Wandering Wisps Special Eyes", "rarity": "mythical", "price": 34.00, "weight": 6000, "image": "images/items/seww.png" },
        { "name": "Unusual Aromatica Bushman", "rarity": "mythical", "price": 23.19, "weight": 6000, "image": "images/items/ba.png" },
        { "name": "Unusual Australium Professional Killstreak Force-A-Nature", "rarity": "unusual", "price": 430.00, "weight": 500, "image": "images/items/aussiefan.png" },
        { "name": "Professional Killstreak Business Class Black Box", "rarity": "rare", "price": 37.90, "weight": 6000, "image": "images/items/bcbb.png" },
        { "name": "Professional Killstreak Steel Brushed Brass Beast", "rarity": "rare", "price": 35.00, "weight": 6000, "image": "images/items/sbbb.png" },
        { "name": "Professional Killstreak Blackout Übersaw", "rarity": "rare", "price": 20.00, "weight": 6000, "image": "images/items/bu.png" },
        { "name": "Genuine Professional Killstreak Machina", "rarity": "genuine", "price": 19.96, "weight": 6000, "image": "images/items/machina.png" },
        { "name": "Strange Professional Killstreak Big Earner", "rarity": "strange", "price": 9.11, "weight": 8000, "image": "images/items/stbigks.png" },
        { "name": "Strange Professional Killstreak Phlogistinator", "rarity": "strange", "price": 21.11, "weight": 5000, "image": "images/items/phlog.png" },
        { "name": "Unusual Disco Beatdown Well-Rounded Rifleman", "rarity": "mythical", "price": 336.11, "weight": 2000, "image": "images/items/dbwrr.png" },
        { "name": "Mann CO. Supply Crate Key ", "rarity": "legendary", "price": 2.50, "weight": 16000, "image": "images/items/key.png" },
        { "name": "Unusual Australium Professional Killstreak Eyelander ", "rarity": "unusual", "price": 630.00, "weight": 200, "image": "images/items/aussieeye.png" }
      ]
    },
    {
      "id": "five",
      "name": "5% Jackpot🎰",
      "price": 85,
      "image": "images/cases/fivejackpot.png",
      "items": [
        { "name": "Unusual Piercing Headache Propaniac", "rarity": "mythical", "price": 750.00, "weight": 1400, "image": "images/items/php1.png" },
        { "name": "Unusual Darkblaze Colonel Kringle", "rarity": "collector", "price": 10000.00, "weight": 100, "image": "images/items/dbcc1.png" },
        { "name": "Unusual Cold Cosmos Brimmed Bootlegger", "rarity": "mythical", "price": 1100.00, "weight": 1100, "image": "images/items/bbcc.png" },
        { "name": "Unusual Flourishing Passion Mean Captain", "rarity": "mythical", "price": 1875.00, "weight": 500, "image": "images/items/mcfp.png" },
        { "name": "Unusual Verdatica Scot Bonnet", "rarity": "mythical", "price": 996.00, "weight": 500, "image": "images/items/vsb.png" },
        { "name": "Unusual Phantom Crown Towering Pillar of Summer Shades", "rarity": "mythical", "price": 1950.00, "weight": 400, "image": "images/items/pcpss.png" },
        { "name": "Unusual Serenus Lumen Mann of the Seven Sees", "rarity": "mythical", "price": 842.00, "weight": 1000, "image": "images/items/motss.png" },
        { "name": "Refined Metal", "rarity": "legendary", "price": 0.03, "weight": 95000, "image": "images/items/refined.png" }
      ]
     },
    {
      "id": "aussie",
      "name": "AUSTRALIUM🪙",
      "price": 45.00,
      "image": "images/cases/aussie.png",
      "items": [
        { "name": "Professional Killstreak Australium Rocket Launcher", "rarity": "legendary", "price": 270.00, "weight": 125, "image": "images/items/aussierocket.png" },
        { "name": "Professional Killstreak Australium Minigun", "rarity": "legendary", "price": 85.00, "weight": 160, "image": "images/items/aussiemini.png" },
        { "name": "Professional Killstreak Australium Knife", "rarity": "legendary", "price": 75.00, "weight": 170, "image": "images/items/aussieknife.png" },
        { "name": "Professional Killstreak Australium Scattergun", "rarity": "legendary", "price": 196.00, "weight": 135, "image": "images/items/aussiescatt.png" },
        { "name": "Professional Killstreak Australium Force-a-Nature", "rarity": "legendary", "price": 54.00, "weight": 195, "image": "images/items/aussiefan.png" },
        { "name": "Professional Killstreak Australium Black Box", "rarity": "legendary", "price": 86.00, "weight": 200, "image": "images/items/aussieblack.png" },
        { "name": "Professional Killstreak Australium Flame Thrower", "rarity": "legendary", "price": 226.00, "weight": 160, "image": "images/items/aussieflame.png" },
        { "name": "Professional Killstreak Australium Axtinguisher", "rarity": "legendary", "price": 21.00, "weight": 195, "image": "images/items/aussieaxt.png" },
        { "name": "Professional Killstreak Australium Grenade Launcher", "rarity": "legendary", "price": 98.00, "weight": 165, "image": "images/items/aussiegrenade.png" },
        { "name": "Professional Killstreak Australium Eyelander", "rarity": "legendary", "price": 150.00, "weight": 275, "image": "images/items/aussieeye.png" },
        { "name": "Professional Killstreak Australium Tomislav", "rarity": "legendary", "price": 82.00, "weight": 150, "image": "images/items/aussietomy.png" },
        { "name": "Professional Killstreak Australium Frontier Justice", "rarity": "legendary", "price": 65.00, "weight": 175, "image": "images/items/aussiefront.png" },
        { "name": "Professional Killstreak Australium Wrench", "rarity": "legendary", "price": 88.00, "weight": 160, "image": "images/items/aussiewrench.png" },
        { "name": "Professional Killstreak Australium Blutsauger", "rarity": "legendary", "price": 18.00, "weight": 200, "image": "images/items/aussieblut.png" },
        { "name": "Professional Killstreak Australium Medigun", "rarity": "legendary", "price": 170.00, "weight": 115, "image": "images/items/aussiemedi.png" },
        { "name": "Professional Killstreak Australium Sniper Rifle", "rarity": "legendary", "price": 115.00, "weight": 155, "image": "images/items/aussiesniper.png" },
        { "name": "Professional Killstreak Australium SMG", "rarity": "legendary", "price": 26.00, "weight": 190, "image": "images/items/aussiesmg.png" },
        { "name": "Scrap Metal", "rarity": "legendary", "price": 0.01, "weight": 5500, "image": "images/items/scrap.png" },
        { "name": "Professional Killstreak Australium Ambassador", "rarity": "legendary", "price": 47.00, "weight": 185, "image": "images/items/aussieamby.png" },
        { "name": "Unusual Community Sparkle Professional Killstreak Festivized Golden Frying Pan", "rarity": "mythical", "price": 99000.00, "weight": 1, "image": "images/items/aussiefrying.png" },
        { "name": "Professional Killstreak Australium Sticky Bomb Launcher", "rarity": "legendary", "price": 90.00, "weight": 170, "image": "images/items/aussiesticky.png" }
      ]
    }
  ]
}
